cglearntemp/CKES_discrete.py
cglearntemp/CKES_gaussian.py
cglearntemp/__init__.py
cglearntemp/ancestralset.py
cglearntemp/as_freq_tb.py
cglearntemp/calculate_deviance.py
cglearntemp/comp_freq_tb.dll
cglearntemp/comp_freq_tb.so
cglearntemp/comp_pat.py
cglearntemp/comp_skel.py
cglearntemp/compress_freq_table.py
cglearntemp/cond_ind_test.dll
cglearntemp/cond_ind_test.so
cglearntemp/controller_gaussian.py
cglearntemp/controller_multinom.py
cglearntemp/draw.py
cglearntemp/freq_table.py
cglearntemp/gaussian_skeleton_mkb.py
cglearntemp/gaussianpclearn.py
cglearntemp/get_multinom_dist.py
cglearntemp/get_normal_dist.py
cglearntemp/get_toy_graph_discrete.py
cglearntemp/get_toy_graph_gaussian.py
cglearntemp/graph.py
cglearntemp/helper.py
cglearntemp/inducedsubgraph.py
cglearntemp/is_chain_graph.py
cglearntemp/isseparated.py
cglearntemp/istriangulated.py
cglearntemp/junctiontree.py
cglearntemp/learn_complex_multinom.py
cglearntemp/learn_complex_norm.py
cglearntemp/learn_skeleton_multinom.py
cglearntemp/learn_skeleton_norm.py
cglearntemp/mbcsp_discrete.py
cglearntemp/mbcsp_gaussian.py
cglearntemp/moralize.py
cglearntemp/multinom_ci_test.py
cglearntemp/multinom_pc_learn.py
cglearntemp/multinom_skeleton_mkb.py
cglearntemp/norm_ci_test.py
cglearntemp/pattern.py
cglearntemp/rmultinom_cg.py
cglearntemp/rnorm_cg.py
cglearntemp/skeleton.py
cglearntemp/toyMulti.csv
cglearntemp/toygraph.csv
cglearntemp/triangulate.py
cglearntemp/ugtojtree.py
cglearntemp/uig_multinom.py
cglearntemp/uig_norm.py
cglearntemp-0.0.4.dist-info/LICENSE
cglearntemp-0.0.4.dist-info/METADATA
cglearntemp-0.0.4.dist-info/WHEEL
cglearntemp-0.0.4.dist-info/top_level.txt
cglearntemp-0.0.4.dist-info/RECORD
